casacore/.aipsrc
casacore/__init__.py
casacore/_tConvert.cpython-313-x86_64-linux-gnu.so
casacore/_version.py
casacore/data/ephemerides/DE200/table.dat
casacore/data/ephemerides/DE200/table.f0
casacore/data/ephemerides/DE200/table.f0i
casacore/data/ephemerides/DE200/table.info
casacore/data/ephemerides/DE200/table.lock
casacore/data/ephemerides/DE405/table.dat
casacore/data/ephemerides/DE405/table.f0
casacore/data/ephemerides/DE405/table.f0i
casacore/data/ephemerides/DE405/table.info
casacore/data/ephemerides/DE405/table.lock
casacore/data/ephemerides/Lines/table.dat
casacore/data/ephemerides/Lines/table.f0
casacore/data/ephemerides/Lines/table.info
casacore/data/ephemerides/Lines/table.lock
casacore/data/ephemerides/Sources/table.dat
casacore/data/ephemerides/Sources/table.f0
casacore/data/ephemerides/Sources/table.info
casacore/data/ephemerides/Sources/table.lock
casacore/data/ephemerides/VGEO/table.dat
casacore/data/ephemerides/VGEO/table.f0
casacore/data/ephemerides/VGEO/table.info
casacore/data/ephemerides/VGEO/table.lock
casacore/data/ephemerides/VTOP/table.dat
casacore/data/ephemerides/VTOP/table.f0
casacore/data/ephemerides/VTOP/table.info
casacore/data/ephemerides/VTOP/table.lock
casacore/data/geodetic/IERSeop2000/table.dat
casacore/data/geodetic/IERSeop2000/table.f0
casacore/data/geodetic/IERSeop2000/table.info
casacore/data/geodetic/IERSeop2000/table.lock
casacore/data/geodetic/IERSeop97/table.dat
casacore/data/geodetic/IERSeop97/table.f0
casacore/data/geodetic/IERSeop97/table.info
casacore/data/geodetic/IERSeop97/table.lock
casacore/data/geodetic/IERSeop97/table.lock.org
casacore/data/geodetic/IERSpredict/table.dat
casacore/data/geodetic/IERSpredict/table.f0
casacore/data/geodetic/IERSpredict/table.info
casacore/data/geodetic/IERSpredict/table.lock
casacore/data/geodetic/IERSpredict.old/table.dat
casacore/data/geodetic/IERSpredict.old/table.f0
casacore/data/geodetic/IERSpredict.old/table.info
python_casacore-3.7.1.dist-info/METADATA
python_casacore-3.7.1.dist-info/WHEEL
python_casacore-3.7.1.dist-info/RECORD
python_casacore-3.7.1.dist-info/licenses/LICENSE
