Metadata-Version: 2.2
Name: python-casacore
Version: 3.7.1
Summary: A wrapper around CASACORE, the radio astronomy library
Keywords: pyrap,casacore,utilities,astronomy
Author-Email: Malte Marquarding <Malte.Marquarding@gmail.com>, Ger van Diepen <gervandiepen@gmail.com>, Gijs Molenaar <gijs@pythonic.nl>, Tammo Jan Dijkema <dijkema@astron.nl>, Marcel Loose <loose@astron.nl>
License:                    GNU LESSER GENERAL PUBLIC LICENSE
Classifier: Development Status :: 5 - Production/Stable
Classifier: Intended Audience :: Science/Research
Classifier: License :: OSI Approved :: GNU Lesser General Public License v3 (LGPLv3)
Classifier: Natural Language :: English
Classifier: Operating System :: POSIX :: Linux
Classifier: Programming Language :: C++
Classifier: Programming Language :: Python :: 3
Classifier: Topic :: Scientific/Engineering :: Astronomy
Project-URL: Homepage, https://github.com/casacore/python-casacore
Requires-Python: >=3.8
Requires-Dist: numpy
